huntela/__init__.py
huntela/constants.py
huntela/search.py
huntela/setup.py
huntela/utils.py
huntela/models/__init__.py
huntela/models/result.py
huntela-0.0.18.dist-info/METADATA
huntela-0.0.18.dist-info/WHEEL
huntela-0.0.18.dist-info/top_level.txt
huntela-0.0.18.dist-info/RECORD
