Metadata-Version: 2.1
Name: huntela
Version: 0.0.18
Summary: Find what you're looking for in a flash with Huntela.
Home-page: https://github.com/CodeLexis/huntela
Author: Tomisin Abiodun
Author-email: decave.12357@gmail.com
License: UNKNOWN
Keywords: python,search,query
Platform: UNKNOWN
Classifier: Development Status :: 4 - Beta
Classifier: Environment :: Console
Classifier: Environment :: Web Environment
Classifier: Intended Audience :: Developers
Classifier: Natural Language :: English
Classifier: Programming Language :: Python
Classifier: Programming Language :: Python :: 3
Classifier: Programming Language :: Python :: 3.7
Classifier: Programming Language :: Python :: 3.8
Classifier: Programming Language :: Python :: 3.9
Classifier: Programming Language :: Python :: 3.10
Classifier: Programming Language :: Python :: 3.11
Classifier: Programming Language :: Python :: 3 :: Only
Classifier: Programming Language :: Python :: Implementation :: CPython
Classifier: Programming Language :: Python :: Implementation :: PyPy
Classifier: Operating System :: MacOS :: MacOS X
Classifier: Operating System :: Microsoft :: Windows
Classifier: Operating System :: POSIX :: Linux
Classifier: Topic :: Software Development :: Libraries
Requires-Python: >=3.9, <4
Requires-Dist: psutil
